address/__init__.py
address/asgi.py
address/settings.py
address/urls.py
address/wsgi.py
drf_address/__init__.py
drf_address/admin.py
drf_address/apps.py
drf_address/models.py
drf_address/pagination.py
drf_address/routers.py
drf_address/serializers.py
drf_address/tests.py
drf_address/urls.py
drf_address/views.py
drf_address/viewsets.py
drf_address/management/__init__.py
drf_address/management/commands/__init__.py
drf_address/management/commands/populate_countries.py
drf_address-0.0.1.dev0.dist-info/LICENSE
drf_address-0.0.1.dev0.dist-info/METADATA
drf_address-0.0.1.dev0.dist-info/WHEEL
drf_address-0.0.1.dev0.dist-info/top_level.txt
drf_address-0.0.1.dev0.dist-info/RECORD
